README.md
setup.py
oneutils/__init__.py
oneutils/datautil.py
oneutils/fileutil.py
oneutils/hello.py
oneutils/textutil.py
oneutils.egg-info/PKG-INFO
oneutils.egg-info/SOURCES.txt
oneutils.egg-info/dependency_links.txt
oneutils.egg-info/top_level.txt