Metadata-Version: 1.0
Name: oneutils
Version: 0.1.2
Summary: utils for text,audio,video,excel,file and so on.
Home-page: https://github.com/yunsansheng/oneutils
Author: henry.wang
Author-email: shanandone@qq.com
License: MIT Licence
Keywords: pip3,henry
Platform: any
